donotimport/__init__.py
donotimport-0.0.2.dist-info/License
donotimport-0.0.2.dist-info/METADATA
donotimport-0.0.2.dist-info/WHEEL
donotimport-0.0.2.dist-info/top_level.txt
donotimport-0.0.2.dist-info/RECORD
